helptools/__init__.py
helptools/urls.py
helptools/views.py
helptools/files/helpTools.js
helptools/files/helpTools.min.js
helptools/files/icon.svg
helptools/files/mic.svg
helptools/files/docs/eng.html
helptools/files/docs/index.html
helptools/files/docs/ru.html
helptools/templatetags/__init__.py
helptools/templatetags/helpTags.py
helptools-0.0.4.dist-info/METADATA
helptools-0.0.4.dist-info/WHEEL
helptools-0.0.4.dist-info/top_level.txt
helptools-0.0.4.dist-info/RECORD
