Metadata-Version: 2.1
Name: helptools
Version: 0.0.4
Summary: The Django version of helpTools.js.
Home-page: UNKNOWN
Author: Just Leo
Author-email: 
License: MIT
Platform: UNKNOWN
Classifier: License :: OSI Approved :: MIT License
Classifier: Programming Language :: Python :: 3
Classifier: Programming Language :: Python :: 3.8
